{
  "annotations": {
    "list": [
      {
        "builtIn": 1,
        "datasource": "-- Grafana --",
        "enable": true,
        "hide": true,
        "iconColor": "rgba(0, 211, 255, 1)",
        "name": "Annotations & Alerts",
        "type": "dashboard"
      }
    ]
  },
  "editable": true,
  "gnetId": null,
  "graphTooltip": 0,
  "id": 37,
  "iteration": 1633724250780,
  "links": [],
  "panels": [
    {
      "datasource": null,
      "description": "",
      "fieldConfig": {
        "defaults": {
          "color": {
            "mode": "thresholds"
          },
          "mappings": [],
          "thresholds": {
            "mode": "absolute",
            "steps": [
              {
                "color": "rgb(60, 60, 60)",
                "value": null
              },
              {
                "color": "semi-dark-green",
                "value": 1
              }
            ]
          }
        },
        "overrides": []
      },
      "gridPos": {
        "h": 7,
        "w": 7,
        "x": 0,
        "y": 0
      },
      "id": 15,
      "options": {
        "colorMode": "value",
        "graphMode": "area",
        "justifyMode": "auto",
        "orientation": "auto",
        "reduceOptions": {
          "calcs": [
            "last"
          ],
          "fields": "",
          "values": false
        },
        "text": {},
        "textMode": "name"
      },
      "pluginVersion": "7.5.5",
      "targets": [
        {
          "exemplar": true,
          "expr": "fio_producer_producing{chain_id=\"$chainid\"}",
          "interval": "",
          "legendFormat": "{{endpoint}}",
          "refId": "A"
        }
      ],
      "timeFrom": null,
      "timeShift": null,
      "title": "Active Producer",
      "transformations": [],
      "transparent": true,
      "type": "stat"
    },
    {
      "datasource": null,
      "description": "",
      "fieldConfig": {
        "defaults": {},
        "overrides": []
      },
      "gridPos": {
        "h": 2,
        "w": 4,
        "x": 10,
        "y": 0
      },
      "id": 17,
      "options": {
        "content": "# &nbsp; &nbsp; ${chainid}\n         ",
        "mode": "markdown"
      },
      "pluginVersion": "7.5.5",
      "timeFrom": null,
      "timeShift": null,
      "transparent": true,
      "type": "text"
    },
    {
      "datasource": null,
      "fieldConfig": {
        "defaults": {
          "color": {
            "mode": "thresholds"
          },
          "mappings": [],
          "thresholds": {
            "mode": "percentage",
            "steps": [
              {
                "color": "rgba(243, 243, 243, 0.53)",
                "value": null
              },
              {
                "color": "dark-purple",
                "value": 50
              },
              {
                "color": "semi-dark-green",
                "value": 90
              }
            ]
          },
          "unit": "locale"
        },
        "overrides": []
      },
      "gridPos": {
        "h": 30,
        "w": 8,
        "x": 16,
        "y": 0
      },
      "id": 12,
      "interval": null,
      "maxDataPoints": null,
      "options": {
        "displayMode": "basic",
        "orientation": "horizontal",
        "reduceOptions": {
          "calcs": [
            "last"
          ],
          "fields": "",
          "values": false
        },
        "showUnfilled": true,
        "text": {}
      },
      "pluginVersion": "7.5.5",
      "targets": [
        {
          "exemplar": true,
          "expr": "sort_desc(fio_producer_votes{chain_id=\"$chainid\",producer=~\"$producer\"})",
          "format": "time_series",
          "interval": "",
          "legendFormat": "{{producer}}",
          "refId": "A"
        }
      ],
      "timeFrom": null,
      "timeShift": null,
      "title": "votes",
      "transformations": [
        {
          "id": "labelsToFields",
          "options": {
            "valueLabel": "producer"
          }
        },
        {
          "id": "sortBy",
          "options": {
            "fields": {},
            "sort": [
              {
                "field": "__name__"
              }
            ]
          }
        }
      ],
      "transparent": true,
      "type": "bargauge"
    },
    {
      "aliasColors": {},
      "bars": false,
      "dashLength": 10,
      "dashes": false,
      "datasource": null,
      "fieldConfig": {
        "defaults": {
          "unit": "s"
        },
        "overrides": []
      },
      "fill": 4,
      "fillGradient": 5,
      "gridPos": {
        "h": 9,
        "w": 9,
        "x": 7,
        "y": 2
      },
      "hiddenSeries": false,
      "id": 6,
      "legend": {
        "alignAsTable": true,
        "avg": false,
        "current": true,
        "max": false,
        "min": false,
        "rightSide": true,
        "show": true,
        "total": false,
        "values": true
      },
      "lines": true,
      "linewidth": 0,
      "nullPointMode": "null",
      "options": {
        "alertThreshold": true
      },
      "percentage": false,
      "pluginVersion": "7.5.5",
      "pointradius": 2,
      "points": false,
      "renderer": "flot",
      "seriesOverrides": [],
      "spaceLength": 10,
      "stack": false,
      "steppedLine": true,
      "targets": [
        {
          "exemplar": true,
          "expr": "fio_info_head_lag{chain_id=\"$chainid\"}",
          "interval": "",
          "legendFormat": "{{endpoint}}",
          "refId": "A"
        }
      ],
      "thresholds": [],
      "timeFrom": null,
      "timeRegions": [],
      "timeShift": null,
      "title": "Catching Up",
      "tooltip": {
        "shared": true,
        "sort": 2,
        "value_type": "individual"
      },
      "transparent": true,
      "type": "graph",
      "xaxis": {
        "buckets": null,
        "mode": "time",
        "name": null,
        "show": true,
        "values": []
      },
      "yaxes": [
        {
          "$$hashKey": "object:342",
          "format": "s",
          "label": null,
          "logBase": 1,
          "max": null,
          "min": "0",
          "show": true
        },
        {
          "$$hashKey": "object:343",
          "format": "short",
          "label": null,
          "logBase": 1,
          "max": null,
          "min": null,
          "show": true
        }
      ],
      "yaxis": {
        "align": false,
        "alignLevel": null
      }
    },
    {
      "datasource": null,
      "fieldConfig": {
        "defaults": {
          "color": {
            "mode": "thresholds"
          },
          "custom": {
            "align": "left",
            "filterable": false
          },
          "mappings": [],
          "thresholds": {
            "mode": "absolute",
            "steps": [
              {
                "color": "dark-blue",
                "value": null
              }
            ]
          },
          "unit": "locale"
        },
        "overrides": []
      },
      "gridPos": {
        "h": 10,
        "w": 7,
        "x": 0,
        "y": 7
      },
      "id": 13,
      "options": {
        "showHeader": true,
        "sortBy": [
          {
            "desc": false,
            "displayName": "Value"
          }
        ]
      },
      "pluginVersion": "7.5.5",
      "targets": [
        {
          "exemplar": true,
          "expr": "max(fio_info_head_block{chain_id=\"$chainid\"}) by (endpoint, version)",
          "interval": "",
          "legendFormat": "{{endpoint}} {{version}}",
          "refId": "A"
        }
      ],
      "title": "Nodeos Version / Block Height",
      "transformations": [
        {
          "id": "reduce",
          "options": {
            "includeTimeField": false,
            "mode": "reduceFields",
            "reducers": [
              "last"
            ]
          }
        },
        {
          "id": "labelsToFields",
          "options": {}
        }
      ],
      "transparent": true,
      "type": "table"
    },
    {
      "aliasColors": {},
      "bars": false,
      "dashLength": 10,
      "dashes": false,
      "datasource": null,
      "fieldConfig": {
        "defaults": {
          "unit": "bits"
        },
        "overrides": []
      },
      "fill": 0,
      "fillGradient": 0,
      "gridPos": {
        "h": 10,
        "w": 9,
        "x": 7,
        "y": 11
      },
      "hiddenSeries": false,
      "id": 2,
      "legend": {
        "alignAsTable": true,
        "avg": false,
        "current": true,
        "hideEmpty": true,
        "hideZero": true,
        "max": false,
        "min": false,
        "rightSide": true,
        "show": true,
        "sort": "current",
        "sortDesc": true,
        "total": false,
        "values": true
      },
      "lines": true,
      "linewidth": 2,
      "nullPointMode": "null",
      "options": {
        "alertThreshold": true
      },
      "percentage": false,
      "pluginVersion": "7.5.5",
      "pointradius": 2,
      "points": false,
      "renderer": "flot",
      "seriesOverrides": [],
      "spaceLength": 10,
      "stack": false,
      "steppedLine": false,
      "targets": [
        {
          "exemplar": true,
          "expr": "fio_db_used_bytes{chain_id=\"$chainid\"}",
          "interval": "",
          "legendFormat": "{{endpoint}}",
          "refId": "A"
        }
      ],
      "thresholds": [],
      "timeFrom": null,
      "timeRegions": [],
      "timeShift": null,
      "title": "state size",
      "tooltip": {
        "shared": true,
        "sort": 2,
        "value_type": "individual"
      },
      "transparent": true,
      "type": "graph",
      "xaxis": {
        "buckets": null,
        "mode": "time",
        "name": null,
        "show": true,
        "values": []
      },
      "yaxes": [
        {
          "$$hashKey": "object:122",
          "format": "bits",
          "label": null,
          "logBase": 1,
          "max": null,
          "min": null,
          "show": true
        },
        {
          "$$hashKey": "object:123",
          "format": "short",
          "label": null,
          "logBase": 1,
          "max": null,
          "min": null,
          "show": true
        }
      ],
      "yaxis": {
        "align": false,
        "alignLevel": null
      }
    },
    {
      "datasource": null,
      "description": "",
      "fieldConfig": {
        "defaults": {
          "color": {
            "mode": "thresholds"
          },
          "custom": {
            "align": null,
            "filterable": false
          },
          "mappings": [],
          "min": 1,
          "thresholds": {
            "mode": "absolute",
            "steps": [
              {
                "color": "light-green",
                "value": null
              },
              {
                "color": "dark-green",
                "value": 15
              },
              {
                "color": "semi-dark-blue",
                "value": 21
              },
              {
                "color": "semi-dark-orange",
                "value": 42
              }
            ]
          }
        },
        "overrides": [
          {
            "matcher": {
              "id": "byName",
              "options": "Last"
            },
            "properties": [
              {
                "id": "custom.displayMode"
              }
            ]
          }
        ]
      },
      "gridPos": {
        "h": 13,
        "w": 7,
        "x": 0,
        "y": 17
      },
      "id": 19,
      "options": {
        "showHeader": true,
        "sortBy": [
          {
            "desc": false,
            "displayName": "Last"
          }
        ]
      },
      "pluginVersion": "7.5.5",
      "targets": [
        {
          "exemplar": true,
          "expr": "fio_producer_rank{chain_id=\"$chainid\", producer=~\"$producer\"}",
          "interval": "",
          "legendFormat": "{{producer}}",
          "refId": "A"
        }
      ],
      "title": "Ranking",
      "transformations": [
        {
          "id": "reduce",
          "options": {
            "reducers": [
              "last"
            ]
          }
        },
        {
          "id": "labelsToFields",
          "options": {}
        },
        {
          "id": "filterByValue",
          "options": {
            "filters": [
              {
                "config": {
                  "id": "greater",
                  "options": {
                    "value": 0
                  }
                },
                "fieldName": "Last"
              }
            ],
            "match": "any",
            "type": "include"
          }
        }
      ],
      "transparent": true,
      "type": "table"
    },
    {
      "aliasColors": {},
      "bars": false,
      "dashLength": 10,
      "dashes": false,
      "datasource": null,
      "fieldConfig": {
        "defaults": {},
        "overrides": []
      },
      "fill": 0,
      "fillGradient": 0,
      "gridPos": {
        "h": 9,
        "w": 9,
        "x": 7,
        "y": 21
      },
      "hiddenSeries": false,
      "id": 10,
      "legend": {
        "alignAsTable": true,
        "avg": false,
        "current": true,
        "hideEmpty": true,
        "hideZero": true,
        "max": false,
        "min": false,
        "rightSide": true,
        "show": true,
        "sort": "current",
        "sortDesc": true,
        "total": false,
        "values": true
      },
      "lines": true,
      "linewidth": 2,
      "nullPointMode": "null",
      "options": {
        "alertThreshold": true
      },
      "percentage": false,
      "pluginVersion": "7.5.5",
      "pointradius": 2,
      "points": false,
      "renderer": "flot",
      "seriesOverrides": [],
      "spaceLength": 10,
      "stack": false,
      "steppedLine": false,
      "targets": [
        {
          "exemplar": true,
          "expr": "fio_net_connected_peers{chain_id=\"$chainid\"}",
          "interval": "",
          "legendFormat": "Peers: {{endpoint}}",
          "refId": "A"
        },
        {
          "exemplar": true,
          "expr": "fio_net_disconnected_peers{chain_id=\"$chainid\"}",
          "hide": true,
          "interval": "",
          "legendFormat": "Failed: {{endpoint}}",
          "refId": "B"
        },
        {
          "exemplar": true,
          "expr": "fio_net_syncing_peers{chain_id=\"$chainid\"}",
          "hide": false,
          "interval": "",
          "legendFormat": "Syncing: {{endpoint}}",
          "refId": "C"
        }
      ],
      "thresholds": [],
      "timeFrom": null,
      "timeRegions": [],
      "timeShift": null,
      "title": "peers",
      "tooltip": {
        "shared": true,
        "sort": 0,
        "value_type": "individual"
      },
      "transparent": true,
      "type": "graph",
      "xaxis": {
        "buckets": null,
        "mode": "time",
        "name": null,
        "show": true,
        "values": []
      },
      "yaxes": [
        {
          "$$hashKey": "object:460",
          "format": "short",
          "label": null,
          "logBase": 1,
          "max": null,
          "min": null,
          "show": true
        },
        {
          "$$hashKey": "object:461",
          "format": "short",
          "label": null,
          "logBase": 1,
          "max": null,
          "min": null,
          "show": true
        }
      ],
      "yaxis": {
        "align": false,
        "alignLevel": null
      }
    }
  ],
  "refresh": "10s",
  "schemaVersion": 27,
  "style": "dark",
  "tags": [],
  "templating": {
    "list": [
      {
        "allValue": null,
        "current": {
          "selected": true,
          "text": "mainnet",
          "value": "mainnet"
        },
        "datasource": null,
        "definition": "label_values({job=\"fio\"}, chain_id)",
        "description": null,
        "error": null,
        "hide": 0,
        "includeAll": false,
        "label": "Chain ID",
        "multi": false,
        "name": "chainid",
        "options": [],
        "query": {
          "query": "label_values({job=\"fio\"}, chain_id)",
          "refId": "StandardVariableQuery"
        },
        "refresh": 1,
        "regex": "",
        "skipUrlSync": false,
        "sort": 2,
        "tagValuesQuery": "",
        "tags": [],
        "tagsQuery": "",
        "type": "query",
        "useTags": false
      },
      {
        "allValue": null,
        "current": {
          "selected": true,
          "text": [
            "All"
          ],
          "value": [
            "$__all"
          ]
        },
        "datasource": null,
        "definition": "label_values({chain_id=\"$chainid\"}, producer)",
        "description": null,
        "error": null,
        "hide": 0,
        "includeAll": true,
        "label": null,
        "multi": true,
        "name": "producer",
        "options": [],
        "query": {
          "query": "label_values({chain_id=\"$chainid\"}, producer)",
          "refId": "StandardVariableQuery"
        },
        "refresh": 1,
        "regex": "",
        "skipUrlSync": false,
        "sort": 0,
        "tagValuesQuery": "",
        "tags": [],
        "tagsQuery": "",
        "type": "query",
        "useTags": false
      }
    ]
  },
  "time": {
    "from": "now-1h",
    "to": "now"
  },
  "timepicker": {},
  "timezone": "",
  "title": "FIO Dashboard",
  "uid": "MXdyH-v7z",
  "version": 13
}
